notecheck/__init__.py
notecheck/py.typed
notecheck/cli/__init__.py
notecheck/cli/__main__.py
notecheck/cli/entry.py
notecheck/lib/__init__.py
notecheck/lib/checker.py
notecheck/lib/prompts.py
notecheck/lib/util.py
notecheck-0.1.0.dist-info/METADATA
notecheck-0.1.0.dist-info/WHEEL
notecheck-0.1.0.dist-info/entry_points.txt
notecheck-0.1.0.dist-info/RECORD
