Metadata-Version: 2.4
Name: notecheck
Version: 0.1.0
Summary: Markdown note proofreading with OpenAI LLMs
Author-email: Kyle Tennison <kyletennison05@gmail.com>
Requires-Python: >=3.12
Requires-Dist: loguru>=0.7.3
Requires-Dist: openai>=1.73.0
Requires-Dist: typer>=0.15.2
